pyrays/__init__.py
pyrays/__main__.py
pyrays/info.py
pyrays/main.py
pyrays-0.2.7.dist-info/licenses/LICENSE
pyrays-0.2.7.dist-info/METADATA
pyrays-0.2.7.dist-info/WHEEL
pyrays-0.2.7.dist-info/entry_points.txt
pyrays-0.2.7.dist-info/top_level.txt
pyrays-0.2.7.dist-info/RECORD
