Metadata-Version: 2.4
Name: PyRays
Version: 0.2.7
Summary: A GitHub template for Python projects using uv
Author-email: Fabio Calefato <fcalefato@gmail.com>
License-Expression: MIT
Requires-Python: >=3.12
License-File: LICENSE
Requires-Dist: pretty-errors>=1.2.25
Requires-Dist: rich>=13.9.4
Requires-Dist: tomlkit>=0.13.2
Provides-Extra: dev
Requires-Dist: mypy>=1.15.0; extra == "dev"
Requires-Dist: pre-commit>=4.1.0; extra == "dev"
Requires-Dist: ruff>=0.9.7; extra == "dev"
Provides-Extra: test
Requires-Dist: pytest>=8.3.4; extra == "test"
Requires-Dist: pytest-cov>=6.0.0; extra == "test"
Requires-Dist: pytest-watch>=4.2.0; extra == "test"
Provides-Extra: docs
Requires-Dist: markdown-callouts>=0.4.0; extra == "docs"
Requires-Dist: mkdocs>=1.6.1; extra == "docs"
Requires-Dist: mkdocs-autorefs>=1.3.1; extra == "docs"
Requires-Dist: mkdocs-material>=9.6.5; extra == "docs"
Requires-Dist: mkdocstrings>=0.28.1; extra == "docs"
Requires-Dist: mkdocstrings-python>=1.16.1; extra == "docs"
Requires-Dist: pygments>=2.19.1; extra == "docs"
Requires-Dist: pymdown-extensions>=10.14.3; extra == "docs"
Dynamic: license-file
